rubus/__init__.py
rubus/admin.py
rubus/authentication.py
rubus/device.py
rubus/http.py
rubus/rubus.py
rubus_cli-1.0.9.dist-info/LICENSE
rubus_cli-1.0.9.dist-info/METADATA
rubus_cli-1.0.9.dist-info/WHEEL
rubus_cli-1.0.9.dist-info/entry_points.txt
rubus_cli-1.0.9.dist-info/top_level.txt
rubus_cli-1.0.9.dist-info/RECORD
