Metadata-Version: 2.1
Name: rubus-cli
Version: 1.0.9
Summary: CLI to interact with a Rubus API instance
Home-page: https://github.com/xiorcale/rubus-cli
Author: xiorcale
Author-email: quentin.vaucher@protonmail.com
License: UNKNOWN
Platform: UNKNOWN
Requires-Python: >=3.6
Requires-Dist: Click
Requires-Dist: requests
